zep2md/__init__.py
zep2md/__main__.py
zep2md-0.1.3.dist-info/METADATA
zep2md-0.1.3.dist-info/WHEEL
zep2md-0.1.3.dist-info/entry_points.txt
zep2md-0.1.3.dist-info/top_level.txt
zep2md-0.1.3.dist-info/RECORD
