Metadata-Version: 2.1
Name: zep2md
Version: 0.1.3
Summary: UNKNOWN
License: UNKNOWN
Platform: UNKNOWN
Requires-Dist: clumper
Requires-Dist: numpy
Requires-Dist: pandas
Requires-Dist: typer
Provides-Extra: dev
Requires-Dist: flake8 ; extra == 'dev'
Requires-Dist: pytest ; extra == 'dev'
Requires-Dist: jupyter ; extra == 'dev'
Requires-Dist: jupyterlab ; extra == 'dev'
